aio_kavenegar/__init__.py
aio_kavenegar/client.py
aio_kavenegar/exceptions.py
aio_kavenegar/types.py
aio_kavenegar-2.0.1.dist-info/LICENSE.md
aio_kavenegar-2.0.1.dist-info/METADATA
aio_kavenegar-2.0.1.dist-info/WHEEL
aio_kavenegar-2.0.1.dist-info/top_level.txt
aio_kavenegar-2.0.1.dist-info/RECORD
